patent_downloader/__init__.py
patent_downloader/cli.py
patent_downloader/downloader.py
patent_downloader/exceptions.py
patent_downloader/file_utils.py
patent_downloader/mcp_server.py
patent_downloader/models.py
patent_downloader/progress_logger.py
patent_downloader-0.4.1.dist-info/METADATA
patent_downloader-0.4.1.dist-info/WHEEL
patent_downloader-0.4.1.dist-info/entry_points.txt
patent_downloader-0.4.1.dist-info/licenses/LICENSE
patent_downloader-0.4.1.dist-info/RECORD
