Metadata-Version: 2.4
Name: patent-downloader
Version: 0.4.1
Summary: A Python SDK for downloading patents from Google Patents with MCP support
Project-URL: Homepage, https://github.com/Edison-A-N/patent_downloader
Project-URL: Repository, https://github.com/Edison-A-N/patent_downloader
Project-URL: Documentation, https://github.com/Edison-A-N/patent_downloader#readme
Project-URL: Issues, https://github.com/Edison-A-N/patent_downloader/issues
Author-email: Edison <zhangn661@gmail.com>
License: MIT
License-File: LICENSE
Keywords: download,google-patents,mcp,patent,sdk
Classifier: Development Status :: 3 - Alpha
Classifier: Intended Audience :: Developers
Classifier: License :: OSI Approved :: MIT License
Classifier: Programming Language :: Python :: 3.10
Classifier: Programming Language :: Python :: 3.11
Classifier: Programming Language :: Python :: 3.12
Requires-Python: >=3.10
Requires-Dist: beautifulsoup4>=4.9.0
Requires-Dist: pydantic>=2.0.0
Requires-Dist: requests>=2.25.0
Requires-Dist: typing-extensions>=4.0.0
Provides-Extra: mcp
Requires-Dist: mcp>=1.13.1; extra == 'mcp'
